pylc_cli/__init__.py
pylc_cli/cache.py
pylc_cli/display_problem.py
pylc_cli/main.py
pylc_cli/run_solution.py
pylc_cli/solve_problem.py
pylc_cli/queries/__init__.py
pylc_cli/queries/graphql.py
pylc_cli/queries/judge.py
pylc_cli/queries/status.py
pylc_cli-20241104.dist-info/METADATA
pylc_cli-20241104.dist-info/WHEEL
pylc_cli-20241104.dist-info/entry_points.txt
pylc_cli-20241104.dist-info/RECORD
