Metadata-Version: 2.3
Name: pylc_cli
Version: 20241104
Summary: A small CLI tool to solve leetcode problems from your favorite text editor!
Project-URL: Homepage, https://github.com/shiina4119/pylc
Project-URL: Issues, https://github.com/shiina4119/pylc/issues
Classifier: Operating System :: OS Independent
Classifier: Programming Language :: Python :: 3
Requires-Python: >=3.10
Requires-Dist: gql[aiohttp]
Requires-Dist: html2text
Requires-Dist: rich
Requires-Dist: tomli-w
Requires-Dist: typer
